{
    "@class": "com.kony.gen.viz.model.component.KVizSwitch",
    "DNDConfig": null,
    "_height_": {
        "type": "string",
        "value": "32dp"
    },
    "_left_": {
        "type": "string",
        "value": "295dp"
    },
    "_margin_": [
        0,
        0,
        0,
        0
    ],
    "_padding_": [
        0,
        0,
        0,
        0
    ],
    "_skin_": "s94b4f7b07e945d6b7aba7ba33cef02b",
    "_top_": {
        "type": "string",
        "value": "305dp"
    },
    "_width_": {
        "type": "string",
        "value": "100dp"
    },
    "canUpdateUI": true,
    "centerx": {
        "type": "string",
        "value": "50%"
    },
    "containerweight": 100,
    "id": "MySwitch01",
    "info": null,
    "iscustomlayout": false,
    "isvisible": true,
    "kiosk": {
        "render": false
    },
    "kuid": "i35ad366b8b64fe787ca0116c64d4bbf",
    "leftsidetext": "ON",
    "name": "kony.ui.Switch",
    "onslide": null,
    "osPlatform": "iphone",
    "osVersion": "iOS7",
    "parent": "MainFlexContainer",
    "pf": "TestForm008",
    "retaincontentalignment": false,
    "retainflexpositionproperties": false,
    "rightsidetext": "OFF",
    "selectedindex": 0,
    "wType": "Switch",
    "widgetalignment": 5,
    "zindex": 1
}